[{"model": "nascar.team", "pk": 1, "fields": {"date_created": "2024-02-27T20:23:51.704Z", "user": 1, "date_updated": "2024-02-27T23:40:51.375Z", "team_name": "Hendrick Motorsports", "manufacturer": 1}}, {"model": "nascar.team", "pk": 2, "fields": {"date_created": "2024-02-27T20:34:14.888Z", "user": 1, "date_updated": "2024-02-27T20:34:14.888Z", "team_name": "JTG Daugherty Racing", "manufacturer": 1}}, {"model": "nascar.team", "pk": 3, "fields": {"date_created": "2024-02-27T20:34:37.943Z", "user": 1, "date_updated": "2024-02-27T20:34:37.943Z", "team_name": "Kaulig Racing", "manufacturer": 1}}, {"model": "nascar.team", "pk": 4, "fields": {"date_created": "2024-02-27T20:37:42.433Z", "user": 1, "date_updated": "2024-02-27T20:37:42.433Z", "team_name": "Richard Childress Racing", "manufacturer": 1}}, {"model": "nascar.team", "pk": 5, "fields": {"date_created": "2024-02-27T20:39:19.878Z", "user": 1, "date_updated": "2024-02-28T00:08:25.835Z", "team_name": "Spire Motorsports", "manufacturer": 1}}, {"model": "nascar.team", "pk": 6, "fields": {"date_created": "2024-02-27T20:41:53.197Z", "user": 1, "date_updated": "2024-02-28T00:07:08.673Z", "team_name": "Trackhouse Racing", "manufacturer": 1}}, {"model": "nascar.team", "pk": 7, "fields": {"date_created": "2024-02-27T20:43:12.808Z", "user": 1, "date_updated": "2024-02-28T00:10:32.803Z", "team_name": "Front Row Motorsports", "manufacturer": 2}}, {"model": "nascar.team", "pk": 8, "fields": {"date_created": "2024-02-27T20:46:47.649Z", "user": 1, "date_updated": "2024-02-28T00:08:12.290Z", "team_name": "RFK Racing", "manufacturer": 2}}, {"model": "nascar.team", "pk": 9, "fields": {"date_created": "2024-02-27T20:47:47.487Z", "user": 1, "date_updated": "2024-02-28T00:11:15.803Z", "team_name": "Rick Ware Racing", "manufacturer": 2}}, {"model": "nascar.team", "pk": 10, "fields": {"date_created": "2024-02-27T20:50:09.890Z", "user": 1, "date_updated": "2024-02-28T00:08:35.511Z", "team_name": "Stewart-Haas Racing", "manufacturer": 2}}, {"model": "nascar.team", "pk": 11, "fields": {"date_created": "2024-02-27T20:52:02.722Z", "user": 1, "date_updated": "2024-02-28T00:09:21.346Z", "team_name": "Team Penske", "manufacturer": 2}}, {"model": "nascar.team", "pk": 12, "fields": {"date_created": "2024-02-27T20:54:16.664Z", "user": 1, "date_updated": "2024-02-28T00:10:02.600Z", "team_name": "Wood Brothers Racing", "manufacturer": 2}}, {"model": "nascar.team", "pk": 13, "fields": {"date_created": "2024-02-27T20:54:53.475Z", "user": 1, "date_updated": "2024-02-28T00:10:18.043Z", "team_name": "23XI Racing", "manufacturer": 3}}, {"model": "nascar.team", "pk": 14, "fields": {"date_created": "2024-02-27T20:55:44.986Z", "user": 1, "date_updated": "2024-02-28T00:09:12.096Z", "team_name": "Joe Gibbs Racing", "manufacturer": 3}}, {"model": "nascar.team", "pk": 15, "fields": {"date_created": "2024-02-27T20:56:01.307Z", "user": 1, "date_updated": "2024-02-28T00:10:52.016Z", "team_name": "Legacy Motor Club", "manufacturer": 3}}, {"model": "nascar.team", "pk": 16, "fields": {"date_created": "2024-02-27T21:00:28.339Z", "user": 1, "date_updated": "2024-02-27T21:00:28.339Z", "team_name": "In-Active", "manufacturer": 1}}, {"model": "nascar.team", "pk": 17, "fields": {"date_created": "2024-02-27T21:01:26.292Z", "user": 1, "date_updated": "2024-02-27T21:01:26.292Z", "team_name": "Live Fast Motorsports", "manufacturer": 1}}]